promptbuilder/__init__.py
promptbuilder/embeddings.py
promptbuilder/prompt_builder.py
promptbuilder/agent/__init__.py
promptbuilder/agent/agent.py
promptbuilder/agent/context.py
promptbuilder/agent/tool.py
promptbuilder/agent/utils.py
promptbuilder/llm_client/__init__.py
promptbuilder/llm_client/aisuite_client.py
promptbuilder/llm_client/anthropic_client.py
promptbuilder/llm_client/base_client.py
promptbuilder/llm_client/bedrock_client.py
promptbuilder/llm_client/config.py
promptbuilder/llm_client/exceptions.py
promptbuilder/llm_client/google_client.py
promptbuilder/llm_client/litellm_client.py
promptbuilder/llm_client/logfire_decorators.py
promptbuilder/llm_client/main.py
promptbuilder/llm_client/openai_client.py
promptbuilder/llm_client/types.py
promptbuilder/llm_client/utils.py
promptbuilder-0.4.42.dist-info/licenses/LICENSE
promptbuilder-0.4.42.dist-info/METADATA
promptbuilder-0.4.42.dist-info/WHEEL
promptbuilder-0.4.42.dist-info/top_level.txt
promptbuilder-0.4.42.dist-info/RECORD
