Metadata-Version: 2.4
Name: promptbuilder
Version: 0.4.42
Summary: Library for building prompts for LLMs
Home-page: https://github.com/kapulkin/promptbuilder
Author: Kapulkin Stanislav
Author-email: kapulkin@gmail.com
Classifier: Programming Language :: Python :: 3
Classifier: License :: OSI Approved :: MIT License
Classifier: Operating System :: OS Independent
Requires-Python: >=3.10
License-File: LICENSE
Requires-Dist: pydantic
Requires-Dist: pytest
Requires-Dist: aisuite-async
Requires-Dist: google-genai>=1.4.0
Requires-Dist: anthropic
Requires-Dist: openai
Requires-Dist: aioboto3
Requires-Dist: litellm
Requires-Dist: httpx
Requires-Dist: aiohttp
Requires-Dist: tiktoken
Dynamic: author
Dynamic: author-email
Dynamic: classifier
Dynamic: description
Dynamic: description-content-type
Dynamic: home-page
Dynamic: license-file
Dynamic: requires-dist
Dynamic: requires-python
Dynamic: summary
